hyperfuel-1.1.1.dist-info/METADATA
hyperfuel-1.1.1.dist-info/WHEEL
hyperfuel-1.1.1.dist-info/license_files/LICENSE
hyperfuel/__init__.py
hyperfuel/hyperfuel.cp312-win32.pyd
hyperfuel-1.1.1.dist-info/RECORD
